{
  "runCount": 1,
  "durationMs": 295386,
  "usage": null,
  "lastRun": {
    "runId": "run-20a8587d-22c0-45b0-9dec-021a136e2bf3",
    "agentId": "agent-a819c53f-ee15-4a2c-8126-a0438298b5f8",
    "durationMs": 295386,
    "usage": null,
    "model": "composer-2.5",
    "status": "finished",
    "finishedAt": "2026-07-09T20:01:50.643Z",
    "githubRunId": "29046132007",
    "githubWorkflow": "Update cycling data"
  },
  "runs": [
    {
      "runId": "run-20a8587d-22c0-45b0-9dec-021a136e2bf3",
      "finishedAt": "2026-07-09T20:01:50.643Z",
      "durationMs": 295386,
      "usage": null,
      "status": "finished",
      "githubRunId": "29046132007"
    }
  ]
}
