{
  "runCount": 1,
  "durationMs": 134908,
  "usage": null,
  "lastRun": {
    "runId": "run-633761a7-dda4-424f-a983-f9be5c715b7a",
    "agentId": "agent-eb889cd1-3c9e-44f9-8eb2-ae26027fc7dd",
    "durationMs": 134908,
    "usage": null,
    "model": "composer-2.5",
    "status": "finished",
    "finishedAt": "2026-07-19T19:18:49.772Z",
    "githubRunId": "29700270863",
    "githubWorkflow": "Update cycling data"
  },
  "runs": [
    {
      "runId": "run-633761a7-dda4-424f-a983-f9be5c715b7a",
      "finishedAt": "2026-07-19T19:18:49.772Z",
      "durationMs": 134908,
      "usage": null,
      "status": "finished",
      "githubRunId": "29700270863"
    }
  ]
}
